vogue/__init__.py
vogue/exceptions.py
vogue/settings.py
vogue/adapter/__init__.py
vogue/adapter/plugin.py
vogue/api/__init__.py
vogue/api/api_v1/__init__.py
vogue/api/api_v1/api.py
vogue/api/api_v1/endpoints/__init__.py
vogue/api/api_v1/endpoints/bioinfo_covid.py
vogue/api/api_v1/endpoints/bioinfo_micro.py
vogue/api/api_v1/endpoints/bioinfo_mip.py
vogue/api/api_v1/endpoints/common_trends.py
vogue/api/api_v1/endpoints/genootype.py
vogue/api/api_v1/endpoints/home.py
vogue/api/api_v1/endpoints/insert_documents.py
vogue/api/api_v1/endpoints/prepps.py
vogue/api/api_v1/endpoints/reagent_labels.py
vogue/api/api_v1/endpoints/sequencing.py
vogue/api/api_v1/endpoints/update.py
vogue/build/__init__.py
vogue/build/application_tag.py
vogue/build/bioinfo_analysis.py
vogue/build/flowcell.py
vogue/build/reagent_label.py
vogue/build/reagent_label_category.py
vogue/build/sample.py
vogue/commands/__init__.py
vogue/commands/base.py
vogue/commands/load/__init__.py
vogue/commands/load/application_tag.py
vogue/commands/load/base.py
vogue/commands/load/flowcell.py
vogue/commands/load/genotype.py
vogue/commands/load/reagent_label.py
vogue/commands/load/reagent_label_category.py
vogue/commands/load/sample.py
vogue/commands/load/bioinfo/__init__.py
vogue/commands/load/bioinfo/base.py
vogue/commands/load/bioinfo/bioinfo_process.py
vogue/commands/load/bioinfo/bioinfo_raw.py
vogue/commands/load/bioinfo/bioinfo_sample.py
vogue/constants/__init__.py
vogue/constants/constants.py
vogue/constants/lims_constants.py
vogue/crud/__init__.py
vogue/crud/create.py
vogue/crud/find.py
vogue/crud/find_plots/__init__.py
vogue/crud/find_plots/genotype.py
vogue/crud/find_plots/home.py
vogue/crud/find_plots/metric_per_month.py
vogue/crud/find_plots/prepps.py
vogue/crud/find_plots/reagent_labels.py
vogue/crud/find_plots/sequencing.py
vogue/crud/find_plots/bioinfo/__init__.py
vogue/crud/find_plots/bioinfo/covid.py
vogue/crud/find_plots/bioinfo/micro.py
vogue/crud/find_plots/bioinfo/qc.py
vogue/load/__init__.py
vogue-3.5.2.dist-info/LICENSE
vogue-3.5.2.dist-info/METADATA
vogue-3.5.2.dist-info/WHEEL
vogue-3.5.2.dist-info/entry_points.txt
vogue-3.5.2.dist-info/top_level.txt
vogue-3.5.2.dist-info/RECORD
