Metadata-Version: 2.1
Name: vogue
Version: 3.5.2
Summary: UNKNOWN
Home-page: https://github.com/Clinical-Genomics/vogue
Author: Maya Brandi
Author-email: maya.brandi@scilifelab.se
License: UNKNOWN
Platform: UNKNOWN
Requires-Dist: genologics
Requires-Dist: click
Requires-Dist: PyYAML
Requires-Dist: pydantic
Requires-Dist: pydantic[dotenv]
Requires-Dist: fastapi
Requires-Dist: pandas
Requires-Dist: gunicorn
Requires-Dist: uvicorn
Requires-Dist: pymongo
Requires-Dist: mongo-adapter
Requires-Dist: jinja2
Requires-Dist: aiofiles
Requires-Dist: python-multipart
